ax_spider/__init__.py
ax_spider/__main__.py
ax_spider/__version__.py
ax_spider/basics/__init__.py
ax_spider/basics/http.py
ax_spider/basics/no_http.py
ax_spider/basics/others.py
ax_spider/basics/protect.py
ax_spider/basics/spider.py
ax_spider/commands/__init__.py
ax_spider/commands/crawl.py
ax_spider/commands/project.py
ax_spider/commands/spider.py
ax_spider/core/__init__.py
ax_spider/core/crawler.py
ax_spider/core/engine.py
ax_spider/core/item.py
ax_spider/core/log.py
ax_spider/core/pool.py
ax_spider/core/run.py
ax_spider/core/signal_handler.py
ax_spider/core/signals.py
ax_spider/core/state.py
ax_spider/settings/__init__.py
ax_spider/settings/default_settings.py
ax_spider/template/run.tmpl
ax_spider/template/project/__init__.tmpl
ax_spider/template/project/item.tmpl
ax_spider/template/project/middleware.tmpl
ax_spider/template/project/pipeline.tmpl
ax_spider/template/project/setting.tmpl
ax_spider/template/spiders/base_spider.tmpl
ax_spider-0.1.4.dist-info/LICENSE
ax_spider-0.1.4.dist-info/METADATA
ax_spider-0.1.4.dist-info/WHEEL
ax_spider-0.1.4.dist-info/entry_points.txt
ax_spider-0.1.4.dist-info/top_level.txt
ax_spider-0.1.4.dist-info/RECORD
